wikiluv/__init__.py
wikiluv/lancodes.py
wikiluv/main.py
wikiluv/utils.py
wikiluv-0.2.0.dist-info/AUTHORS
wikiluv-0.2.0.dist-info/LICENSE
wikiluv-0.2.0.dist-info/METADATA
wikiluv-0.2.0.dist-info/WHEEL
wikiluv-0.2.0.dist-info/entry_points.txt
wikiluv-0.2.0.dist-info/RECORD
