Metadata-Version: 2.1
Name: wikiluv
Version: 0.2.0
Summary: Wikipedia at your fingertips
License: MIT
Author: walid
Author-email: walid.sa3d@gmail.com
Requires-Python: >=3.10,<4.0
Classifier: License :: OSI Approved :: MIT License
Classifier: Programming Language :: Python :: 3
Classifier: Programming Language :: Python :: 3.10
Classifier: Programming Language :: Python :: 3.11
Classifier: Programming Language :: Python :: 3.12
Classifier: Programming Language :: Python :: 3.13
Requires-Dist: click (>=8.1.7,<9.0.0)
Requires-Dist: pyhyphen (>=4.0.4,<5.0.0)
Requires-Dist: requests (>=2.32.3,<3.0.0)
Requires-Dist: rich (>=13.8.0,<14.0.0)
Requires-Dist: termcolor (>=2.4.0,<3.0.0)
